lib/Cache.py
lib/DaskFile.py
lib/DateTime.py
lib/DebugManager.py
lib/File.py
lib/Filter.py
lib/GDrive.py
lib/Logger.py
lib/Mail.py
lib/MySQL.py
lib/Params.py
lib/S3.py
lib/Summary.py
lib/__init__.py
lib/basic.py
lib/db.py
lib/fn.py
tests/__init__.py
tests/test_apriori.py
product_relation-1.0.0.dist-info/LICENSE
product_relation-1.0.0.dist-info/METADATA
product_relation-1.0.0.dist-info/WHEEL
product_relation-1.0.0.dist-info/entry_points.txt
product_relation-1.0.0.dist-info/top_level.txt
product_relation-1.0.0.dist-info/RECORD
